[
  {
    "brand": "BIXBI",
    "title": "Buy 2, Get 1 FREE on All Treats",
    "image": "https://secure.astroloyalty.com/display_image.php?ec=z53mi3VCNs5cWynSA%2BBvl6vCIw%3D%3D",
    "validity": "11/01/2025 to 11/30/2025"
  },
  {
    "brand": "Blue Buffalo",
    "title": "$5.00 OFF 30lb Life Protection Dry Dog Food",
    "image": "https://secure.astroloyalty.com/display_image.php?ec=z53mi3VCNs5cWyrUGfxtlK%2FB",
    "validity": "11/01/2025 to 11/30/2025"
  },
  {
    "brand": "Blue Buffalo",
    "title": "$2.00 OFF Tastesfuls 7lb Dry Cat Food",
    "image": "https://secure.astroloyalty.com/display_image.php?ec=z53mi3VCNs5cWyrUGfxtlK%2FD",
    "validity": "11/01/2025 to 11/30/2025"
  },
  {
    "brand": "Blue Buffalo",
    "title": "$4.00 OFF 15lb Life Protection Dry Dog Food",
    "image": "https://secure.astroloyalty.com/display_image.php?ec=z53mi3VCNs5cWyrUGfxtlK%2FA",
    "validity": "11/01/2025 to 11/30/2025"
  },
  {
    "brand": "Blue Buffalo",
    "title": "$2.00 OFF Dog Treats",
    "image": "https://secure.astroloyalty.com/display_image.php?ec=z53mi3VCNs5cWyrUGfxtlK%2FC",
    "validity": "11/01/2025 to 11/30/2025"
  },
  {
    "brand": "Bocce's Bakery",
    "title": "$1.00 OFF Everday Training Bites",
    "image": "https://secure.astroloyalty.com/display_image.php?ec=z53mi3VCNs5cWyvWB%2BBvl6vDKg%3D%3D",
    "validity": "11/01/2025 to 11/30/2025"
  },
  {
    "brand": "Canidae",
    "title": "$5.00 OFF Small Bags of Dry Dog Food",
    "image": "https://secure.astroloyalty.com/display_image.php?ec=z53mi3VCNs5cWyvVGfxtkqjH",
    "validity": "11/01/2025 to 11/30/2025"
  },
  {
    "brand": "Fresh News (Targeted Pet Care)",
    "title": "$5.00 OFF Select Products",
    "image": "https://secure.astroloyalty.com/display_image.php?ec=z53mi3VCNs5cWyvfDuBvl63AJw%3D%3D",
    "validity": "11/01/2025 to 11/30/2025"
  },
  {
    "brand": "Fromm Family Foods",
    "title": "$5.00 OFF Gold Dry Cat Food",
    "image": "https://secure.astroloyalty.com/display_image.php?ec=z53mi3VCNs5cWy3QGfxtl6nB",
    "validity": "09/28/2025 to 11/30/2025"
  },
  {
    "brand": "Health Extension",
    "title": "$5.00 OFF Dry Cat Food",
    "image": "https://secure.astroloyalty.com/display_image.php?ec=z53mi3VCNs5cWynTAuBvl6vEJg%3D%3D",
    "validity": "11/01/2025 to 11/30/2025"
  },
  {
    "brand": "Inaba",
    "title": "",
    "image": "https://secure.astroloyalty.com/display_image.php?ec=z53mi3VCNs5cWy3SD%2BBvl6zBKw%3D%3D",
    "validity": "11/01/2025 to 11/30/2025"
  },
  {
    "brand": "Lotus",
    "title": "Dollars OFF Oven-Baked Dog Kibble",
    "image": "https://secure.astroloyalty.com/display_image.php?ec=z53mi3VCNs5cWynWAOBvl6zAKg%3D%3D",
    "validity": "11/01/2025 to 11/30/2025"
  },
  {
    "brand": "Natural Balance",
    "title": "$5.00 OFF Small Bags of Dry Dog Food",
    "image": "https://secure.astroloyalty.com/display_image.php?ec=z53mi3VCNs5cWyvVGfxtkqrD",
    "validity": "11/01/2025 to 11/30/2025"
  },
  {
    "brand": "Natural Balance",
    "title": "$5.00 OFF Small Bags of Dry Cat Food",
    "image": "https://secure.astroloyalty.com/display_image.php?ec=z53mi3VCNs5cWyvVGfxtkqrC",
    "validity": "11/01/2025 to 11/30/2025"
  },
  {
    "brand": "Natures Logic",
    "title": "$6.00 OFF Large Bags of Distinction",
    "image": "https://secure.astroloyalty.com/display_image.php?ec=z53mi3VCNs5cWyHVGfxtk6HJ",
    "validity": "11/01/2025 to 11/30/2025"
  },
  {
    "brand": "Nutri Source",
    "title": "$10.00 OFF 26lb Chicken Free Formulas!",
    "image": "https://secure.astroloyalty.com/display_image.php?ec=z53mi3VCNs5cWyvXGfxtkqzE",
    "validity": "11/01/2025 to 12/31/2025"
  },
  {
    "brand": "Pestell (Targeted Pet Care)",
    "title": "Dollars OFF Select Easy Clean Clumping Litter",
    "image": "https://secure.astroloyalty.com/display_image.php?ec=z53mi3VCNs5cWyvfGfxtkqvI",
    "validity": "11/01/2025 to 11/30/2025"
  },
  {
    "brand": "Raised Right Pets",
    "title": "$1.00 OFF 16oz Veterinary Support Recipes",
    "image": "https://secure.astroloyalty.com/display_image.php?ec=z53mi3VCNs5cWyrTBOBvl6rJJA%3D%3D",
    "validity": "11/01/2025 to 11/30/2025"
  },
  {
    "brand": "Stella and Chewy's",
    "title": "Buy 2, Get 1 FREE on 16oz FreshMade",
    "image": "https://secure.astroloyalty.com/display_image.php?ec=z53mi3VCNs5cWyHSGfxtlKDH",
    "validity": "11/01/2025 to 11/30/2025"
  },
  {
    "brand": "Stella and Chewy's",
    "title": "$5.00 OFF 3.5lb Baked Kibble",
    "image": "https://secure.astroloyalty.com/display_image.php?ec=z53mi3VCNs5cWyHSGfxtlKDE",
    "validity": "11/01/2025 to 11/30/2025"
  },
  {
    "brand": "The Honest Kitchen",
    "title": "$10.00 OFF 4lb-5lb Clusters",
    "image": "https://secure.astroloyalty.com/display_image.php?ec=z53mi3VCNs5cWy7SGfxtkq3J",
    "validity": "11/01/2025 to 11/30/2025"
  }
]